{
    "os": "Linux-6.5.0-45-generic-x86_64-with-glibc2.17",
    "python": "3.8.19",
    "heartbeatAt": "2024-08-12T21:41:18.598693",
    "startedAt": "2024-08-12T21:41:17.838676",
    "docker": null,
    "cuda": null,
    "args": [],
    "state": "running",
    "program": "/home/keyi/Documents/VsCodeP/research/retarget/bimanual/assistive_stable_baselines3/main/train_imitate_dexmv.py",
    "codePathLocal": "main/train_imitate_dexmv.py",
    "codePath": "main/train_imitate_dexmv.py",
    "git": {
        "remote": "https://github.com/DLR-RM/stable-baselines3.git",
        "commit": "4a1137ba3ac0ff0ae095aca564edc82ec37b7f1c"
    },
    "email": "keyiwang2000@gmail.com",
    "root": "/home/keyi/Documents/VsCodeP/research/retarget/bimanual/assistive_stable_baselines3",
    "host": "keyi-Legion-Y7000P-IRH8",
    "username": "keyi",
    "executable": "/home/keyi/anaconda3/envs/artigrasp/bin/python",
    "cpu_count": 10,
    "cpu_count_logical": 16,
    "cpu_freq": {
        "current": 1341.3928750000002,
        "min": 400.0,
        "max": 4475.0
    },
    "cpu_freq_per_core": [
        {
            "current": 1056.107,
            "min": 400.0,
            "max": 4700.0
        },
        {
            "current": 1121.364,
            "min": 400.0,
            "max": 4700.0
        },
        {
            "current": 1082.38,
            "min": 400.0,
            "max": 4700.0
        },
        {
            "current": 915.971,
            "min": 400.0,
            "max": 4700.0
        },
        {
            "current": 1132.921,
            "min": 400.0,
            "max": 4900.0
        },
        {
            "current": 1156.393,
            "min": 400.0,
            "max": 4900.0
        },
        {
            "current": 1105.813,
            "min": 400.0,
            "max": 4900.0
        },
        {
            "current": 1151.012,
            "min": 400.0,
            "max": 4900.0
        },
        {
            "current": 1137.918,
            "min": 400.0,
            "max": 4700.0
        },
        {
            "current": 1109.278,
            "min": 400.0,
            "max": 4700.0
        },
        {
            "current": 1113.474,
            "min": 400.0,
            "max": 4700.0
        },
        {
            "current": 1154.652,
            "min": 400.0,
            "max": 4700.0
        },
        {
            "current": 1034.917,
            "min": 400.0,
            "max": 3600.0
        },
        {
            "current": 1057.178,
            "min": 400.0,
            "max": 3600.0
        },
        {
            "current": 1053.825,
            "min": 400.0,
            "max": 3600.0
        },
        {
            "current": 1088.144,
            "min": 400.0,
            "max": 3600.0
        }
    ],
    "disk": {
        "/": {
            "total": 146.5873565673828,
            "used": 128.36366653442383
        }
    },
    "gpu": "NVIDIA GeForce RTX 4060 Laptop GPU",
    "gpu_count": 1,
    "gpu_devices": [
        {
            "name": "NVIDIA GeForce RTX 4060 Laptop GPU",
            "memory_total": 8585740288
        }
    ],
    "memory": {
        "total": 15.338008880615234
    }
}
